affprop/__init__.py
affprop663/__init__.py
affprop-0.0.3.dist-info/LICENSE
affprop-0.0.3.dist-info/METADATA
affprop-0.0.3.dist-info/WHEEL
affprop-0.0.3.dist-info/top_level.txt
affprop-0.0.3.dist-info/RECORD
