Metadata-Version: 2.1
Name: affprop
Version: 0.0.3
Summary: A package to perform affinity propagation clustering
Home-page: https://github.com/thiesben/affinity-propagation-python
Author: Ben Thies
Author-email: mail@benthies.de
License: UNKNOWN
Project-URL: Bug Tracker, https://github.com/thiesben/affinity-propagation-python/issues
Platform: UNKNOWN
Classifier: Programming Language :: Python :: 3
Classifier: License :: OSI Approved :: MIT License
Classifier: Operating System :: OS Independent
Requires-Python: >=3.7
Requires-Dist: matplotlib
Requires-Dist: numpy
Requires-Dist: typing
